Workbook

Sheet PRUEBA_HISTÓRICO
B3: AÑO | C3: TRIMESTRE | D3: MES | E3: DIA | F3: DEMANDA | H3: DEMANDA PERDIDA | I3: ALMACEN | J3: CAMION | K3: EN PROCESO | M3: CAPACIDAD | N3: ROP | Q3: INICIO
B4: - | C4: - | D4: - | E4: 0 | F4: - | H4: - | I4: 0 | K4: 150 | M4: 20 | N4: 150
B5: 2025 | C5: I | D5: Enero | E5: 1 | F5: 12 | H5: 12 | I5: 0 | K5: 150 | M5: 20 | N5: 150 | Q5: Ingresos
E6: 2 | F6: 40 | H6: 40 | I6: 0 | K6: 150 | M6: 20 | N6: 150 | Q6: Precio por bidón | R6: 1450 | S6: Ingreso por unidad vendida
E7: 3 | F7: 45 | H7: 45 | I7: 0 | K7: 150 | M7: 20 | N7: 150 | Q7: Costos de Pedido
E8: 4 | F8: 34 | H8: 34 | I8: 0 | K8: 150 | M8: 20 | N8: 150 | Q8: Costo por pedido (S) | R8: 1500 | S8: Costo fijo por cada lote de producción activado
E9: 5 | F9: 37 | H9: 37 | I9: 0 | K9: 150 | M9: 20 | N9: 150 | Q9: Costo unitario producción | R9: 1000 | S9: Costo variable por cada bidón producido
E10: 6 | F10: 45 | H10: 45 | I10: 0 | K10: 150 | M10: 20 | N10: 150 | Q10: Costos de Inventario
E11: 7 | F11: 38 | H11: 38 | I11: 0 | J11: 150 | K11: 150 | M11: ="10 - 10" -> 10 - 10 | N11: 150 | Q11: Costo inventario anual (H) | R11: 100 | S11: Costo de mantener un bidón en almacén por un año
E12: 8 | F12: 32 | H12: 32 | I12: 0 | J12: 150 | K12: 150 | M12: 20 | N12: 150 | Q12: Costos de Envío
E13: 9 | F13: 33 | H13: 33 | I13: 0 | J13: 150 | K13: 150 | M13: 20 | N13: 150 | Q13: Costo envío por camión | R13: 15000 | S13: Costo fijo para envíos de hasta 200 bidones
E14: 10 | F14: 40 | H14: 40 | I14: 0 | J14: 150 | K14: 150 | M14: 20 | N14: 150 | Q14: Costo envío por correo | R14: 150 | S14: Costo por bidón para envíos individuales
E15: 11 | F15: 36 | H15: 36 | I15: 0 | J15: 150 | K15: 150 | M15: 20 | N15: 150 | Q15: Tiempos de Entrega
E16: 12 | F16: 44 | H16: 44 | I16: 0 | J16: 150 | K16: 150 | M16: 20 | N16: 150 | Q16: Lead Time camión (LTc) | R16: 7 | S16: Días que tarda en llegar un pedido por camión
E17: 13 | F17: 35 | H17: 35 | I17: 0 | J17: 150 | K17: 150 | M17: 20 | N17: 150 | Q17: Lead Time correo (LTm) | R17: 1 | S17: Días que tarda en llegar un pedido por correo
E18: 14 | F18: 44 | H18: 27 | I18: 150 | K18: 150 | M18: 20 | N18: 150 | Q18: Operaciones
E19: 15 | F19: 48 | H19: 0 | I19: =I18-F19-F18 -> 58 | J19: 150 | K19: 150 | M19: 20 | N19: 150 | Q19: Capacidad actual fábrica | R19: 20 | S19: Máximo de bidones que se pueden producir por día
E20: 16 | F20: 51 | H20: 0 | I20: =I19-F20 -> 7 | J20: 150 | K20: 150 | M20: 20 | N20: 150 | Q20: Financieros
E21: 17 | F21: 37 | H21: 3 | I21: 0 | J21: 150 | K21: 150 | M21: 20 | N21: 150 | Q21: Interés efectivo diario | R21: 0.0002739726 | S21: Tasa de interés diaria que genera el efectivo disponible
E22: 18 | F22: 34 | H22: 34 | I22: 0 | J22: 150 | K22: 150 | M22: 20 | N22: 150
E23: 19 | F23: 44 | H23: 44 | I23: 0 | J23: 150 | K23: 150 | M23: 20 | N23: 150
E24: 20 | F24: 32 | H24: 32 | I24: 0 | J24: 150 | K24: 150 | M24: 20 | N24: 150
E25: 21 | F25: 45 | H25: 45 | I25: 0 | J25: 150 | K25: 150 | M25: 20 | N25: 150
E26: 22 | F26: 53 | H26: 0 | I26: 150 | K26: 150 | M26: ="10 - 10" -> 10 - 10 | N26: 150
E27: 23 | F27: 48 | H27: 0 | I27: =I26-F27-F26 -> 49 | J27: 150 | K27: 150 | M27: 20 | N27: 150
E28: 24 | F28: 28 | H28: 0 | I28: =I27-F28 -> 21 | J28: 150 | K28: 150 | M28: 20 | N28: 150
E29: 25 | F29: 45 | H29: 24 | I29: 0 | J29: 150 | K29: 150 | M29: 20 | N29: 150
E30: 26 | F30: 36 | H30: 36 | I30: 0 | J30: 150 | K30: 150 | M30: 20 | N30: 150
E31: 27 | F31: 32 | H31: 32 | I31: 0 | J31: 150 | K31: 150 | M31: 20 | N31: 150
E32: 28 | F32: 50 | H32: 50 | I32: 0 | J32: 150 | K32: 150 | M32: 20 | N32: 150
E33: 29 | F33: 26 | H33: 11 | I33: 0 | J33: 150 | K33: 150 | M33: 20 | N33: 150
E34: 30 | F34: 43 | H34: 0 | I34: 150 | K34: 150 | M34: 20 | N34: 150
E35: 31 | F35: 54 | H35: 0 | I35: =I34-F35-F34 -> 53 | J35: 150 | K35: 150 | M35: 20 | N35: 150
D36: Febrero | E36: 32 | F36: 45 | H36: 7 | I36: =I35-F36 -> 8 | J36: 150 | K36: 150 | M36: 20 | N36: 150
E37: 33 | F37: 39 | H37: 39 | I37: 0 | J37: 150 | K37: 150 | M37: 20 | N37: 150
E38: 34 | F38: 39 | H38: 39 | I38: 0 | J38: 150 | K38: 150 | M38: 20 | N38: 150
E39: 35 | F39: 51 | H39: 51 | I39: 0 | J39: 150 | K39: 150 | M39: 20 | N39: 150
E40: 36 | F40: 49 | H40: 49 | I40: 0 | J40: 150 | K40: 150 | M40: 20 | N40: 150
E41: 37 | F41: 35 | H41: 0 | I41: 0 | J41: 150 | K41: 150 | M41: ="10 - 10" -> 10 - 10 | N41: 150
E42: 38 | F42: 45 | H42: 0 | I42: 150 | K42: 150 | M42: 20 | N42: 150
E43: 39 | F43: 45 | H43: 0 | I43: =I42-F43-F42 -> 60 | J43: 150 | K43: 150 | M43: 20 | N43: 150
E44: 40 | F44: 40 | H44: 15 | I44: =I43-F44 -> 20 | J44: 150 | K44: 150 | M44: 20 | N44: 150
E45: 41 | F45: 37 | H45: 37 | I45: 0 | J45: 150 | K45: 150 | M45: 20 | N45: 150
E46: 42 | F46: 52 | H46: 52 | I46: 0 | J46: 150 | K46: 150 | M46: 20 | N46: 150
E47: 43 | F47: 43 | H47: 43 | I47: 0 | J47: 150 | K47: 150 | M47: 20 | N47: 150
E48: 44 | F48: 42 | H48: 24 | I48: 0 | J48: 150 | K48: 150 | M48: 20 | N48: 150
E49: 45 | F49: 52 | H49: 0 | I49: 0 | J49: 150 | K49: 150 | M49: 20 | N49: 150
E50: 46 | F50: 41 | H50: 0 | I50: 150 | K50: 150 | M50: 20 | N50: 150
E51: 47 | F51: 43 | H51: 4 | I51: =I50-F51-F50 -> 66 | J51: 150 | K51: 150 | M51: 20 | N51: 150
E52: 48 | F52: 45 | H52: 45 | I52: =I51-F52 -> 21 | J52: 150 | K52: 150 | M52: 20 | N52: 150
E53: 49 | F53: 30 | H53: 30 | I53: 0 | J53: 150 | K53: 150 | M53: 20 | N53: 150
E54: 50 | F54: 40 | H54: 40 | I54: 0 | J54: 150 | K54: 150 | M54: 20 | N54: 150
E55: 51 | F55: 35 | H55: 35 | I55: 0 | J55: 150 | K55: 150 | M55: 20 | N55: 150
E56: 52 | F56: 53 | H56: 0 | I56: 0 | J56: 150 | K56: 150 | M56: ="10 - 10" -> 10 - 10 | N56: 150
E57: 53 | F57: 44 | H57: 0 | I57: 0 | J57: 150 | K57: 150 | M57: 20 | N57: 150
E58: 54 | F58: 40 | H58: 0 | I58: 150 | K58: 150 | M58: 20 | N58: 150
E59: 55 | F59: 48 | H59: 35 | I59: =I58-F59-F58 -> 62 | J59: 150 | K59: 150 | M59: 20 | N59: 150
E60: 56 | F60: 46 | H60: 46 | I60: =I59-F60 -> 16 | J60: 150 | K60: 150 | M60: 20 | N60: 150
E61: 57 | F61: 41 | H61: 41 | I61: 0 | J61: 150 | K61: 150 | M61: 20 | N61: 150
E62: 58 | F62: 48 | H62: 48 | I62: 0 | J62: 150 | K62: 150 | M62: 20 | N62: 150
E63: 59 | F63: 51 | H63: 19 | I63: 0 | J63: 150 | K63: 150 | M63: 20 | N63: 150
D64: Marzo | E64: 60 | F64: 47 | H64: 0 | I64: 0 | J64: 150 | K64: 150 | M64: 20 | N64: 150
E65: 61 | F65: 45 | H65: 0 | I65: 0 | J65: 150 | K65: 150 | M65: 20 | N65: 150
E66: 62 | F66: 34 | H66: 8 | I66: 150 | K66: 150 | M66: 20 | N66: 150
E67: 63 | F67: 37 | H67: 37 | I67: =I66-F67-F66 -> 79 | J67: 150 | K67: 150 | M67: 20 | N67: 150
E68: 64 | F68: 34 | H68: 34 | I68: =I67-F68 -> 45 | J68: 150 | K68: 150 | M68: 20 | N68: 150
E69: 65 | F69: 49 | H69: 49 | I69: 0 | J69: 150 | K69: 150 | M69: 20 | N69: 150
E70: 66 | F70: 39 | H70: 39 | I70: 0 | J70: 150 | K70: 150 | M70: 20 | N70: 150
E71: 67 | F71: 61 | H71: 0 | I71: 0 | J71: 150 | K71: 150 | M71: ="10 - 10" -> 10 - 10 | N71: 150
E72: 68 | F72: 55 | H72: 0 | I72: 0 | J72: 150 | K72: 150 | M72: 20 | N72: 150
E73: 69 | F73: 53 | H73: 19 | I73: 0 | J73: 150 | K73: 150 | M73: 20 | N73: 150
E74: 70 | F74: 30 | H74: 30 | I74: 150 | K74: 150 | M74: 20 | N74: 150
E75: 71 | F75: 50 | H75: 50 | I75: =I74-F75-F74 -> 70 | J75: 150 | K75: 150 | M75: 20 | N75: 150
E76: 72 | F76: 44 | H76: 44 | I76: =I75-F76 -> 26 | J76: 150 | K76: 150 | M76: 20 | N76: 150
E77: 73 | F77: 40 | H77: 40 | I77: 0 | J77: 150 | K77: 150 | M77: 20 | N77: 150
E78: 74 | F78: 44 | H78: 20 | I78: 0 | J78: 150 | K78: 150 | M78: 20 | N78: 150
E79: 75 | F79: 51 | H79: 0 | I79: 0 | J79: 150 | K79: 150 | M79: 20 | N79: 150
E80: 76 | F80: 46 | H80: 0 | I80: 0 | J80: 150 | K80: 150 | M80: 20 | N80: 150
E81: 77 | F81: 41 | H81: 12 | I81: 0 | J81: 150 | K81: 150 | M81: 20 | N81: 150
E82: 78 | F82: 43 | H82: 43 | I82: 150 | K82: 150 | M82: 20 | N82: 150
E83: 79 | F83: 59 | H83: 59 | I83: =I82-F83-F82 -> 48 | J83: 150 | K83: 150 | M83: 20 | N83: 150
E84: 80 | F84: 45 | H84: 45 | I84: =I83-F84 -> 3 | J84: 150 | K84: 150 | M84: 20 | N84: 150
E85: 81 | F85: 33 | H85: 33 | I85: 0 | J85: 150 | K85: 150 | M85: 20 | N85: 150
E86: 82 | F86: 42 | H86: 0 | I86: 0 | J86: 150 | K86: 150 | M86: ="10 - 10" -> 10 - 10 | N86: 150
E87: 83 | F87: 40 | H87: 0 | I87: 0 | J87: 150 | K87: 150 | M87: 20 | N87: 150
E88: 84 | F88: 47 | H88: 0 | I88: 0 | J88: 150 | K88: 150 | M88: 20 | N88: 150
E89: 85 | F89: 53 | H89: 32 | I89: 0 | J89: 150 | K89: 150 | M89: 20 | N89: 150
E90: 86 | F90: 44 | H90: 44 | I90: 150 | K90: 150 | M90: 20 | N90: 150
E91: 87 | F91: 42 | H91: 42 | I91: =I90-F91-F90 -> 64 | J91: 150 | K91: 150 | M91: 20 | N91: 150
E92: 88 | F92: 38 | H92: 38 | I92: =I91-F92 -> 26 | J92: 150 | K92: 150 | M92: 20 | N92: 150
E93: 89 | F93: 51 | H93: 24 | I93: 0 | J93: 150 | K93: 150 | M93: 20 | N93: 150
E94: 90 | F94: 44 | H94: 0 | I94: 0 | J94: 150 | K94: 150 | M94: 20 | N94: 150
C95: II | D95: Abril | E95: 91 | F95: 32 | H95: 0 | I95: 0 | J95: 150 | K95: 150 | M95: 20 | N95: 150
E96: 92 | F96: 34 | H96: 0 | I96: 0 | J96: 150 | K96: 150 | M96: 20 | N96: 150
E97: 93 | F97: 50 | H97: 37 | I97: 0 | J97: 150 | K97: 150 | M97: 20 | N97: 150
E98: 94 | F98: 47 | H98: 47 | I98: 150 | K98: 150 | M98: 20 | N98: 150
E99: 95 | F99: 43 | H99: 43 | I99: =I98-F99-F98 -> 60 | J99: 150 | K99: 150 | M99: 20 | N99: 150
E100: 96 | F100: 37 | H100: 37 | I100: =I99-F100 -> 23 | J100: 150 | K100: 150 | M100: 20 | N100: 150
E101: 97 | F101: 41 | H101: 0 | I101: 0 | J101: 150 | K101: 150 | M101: ="10 - 10" -> 10 - 10 | N101: 150
E102: 98 | F102: 36 | H102: 0 | I102: 0 | J102: 150 | K102: 150 | M102: 20 | N102: 150
...

Sheet PROYECCIÓN_PREVISIÓN_EDITAR
B1: AÑO | C1: TRIMESTRE | D1: MES | E1: DIA | F1: DEMANDA | H1: ALMACEN | I1: CAMION | J1: EN PROCESO | L1: CAPACIDAD | M1: ROP | Y1: HORA | Z1: DÍA
B2: - | C2: - | D2: - | E2: 730 | F2: =PRUEBA_HISTÓRICO!F734 -> 24 | H2: 0 | I2: 150 | J2: 150 | L2: 20 | M2: 1200 | Y2: 10.916667 | Z2: 0
B3: 2027 | C3: I | D3: Enero | E3: 731 | F3: =DEMANDA_PREVISIÓN!E735 -> 44 | H3: 0 | I3: 150 | J3: 150 | L3: 20 | M3: 1200 | Y3: 10.926273
E4: 732 | F4: =DEMANDA_PREVISIÓN!E736 -> 41 | H4: 0 | I4: 150 | J4: 150 | L4: 20 | M4: 1200 | Y4: 10.93588
E5: 733 | F5: =DEMANDA_PREVISIÓN!E737 -> 41 | H5: 0 | I5: 150 | J5: 150 | L5: 20 | M5: 1200 | Y5: 10.945486
E6: 734 | F6: =DEMANDA_PREVISIÓN!E738 -> 54 | H6: 150 | J6: 150 | L6: 20 | M6: 1200 | Y6: 10.955093
E7: 735 | F7: =DEMANDA_PREVISIÓN!E739 -> 40 | H7: =H6-F7 -> 110 | I7: 150 | J7: 150 | L7: 20 | M7: 1200 | Y7: 10.964699
E8: 736 | F8: =DEMANDA_PREVISIÓN!E740 -> 46 | H8: =H7-F8 -> 64 | I8: 150 | J8: 200 | L8: 20 | M8: 1200 | Y8: 10.974306
E9: 737 | F9: =DEMANDA_PREVISIÓN!E741 -> 33 | H9: =H8-F9 -> 31 | I9: 150 | J9: 200 | L9: 20 | M9: 1200 | Y9: 10.983912
E10: 738 | F10: =DEMANDA_PREVISIÓN!E742 -> 46 | H10: 0 | I10: 150 | J10: 200 | L10: 20 | M10: 1200 | Y10: 10.993519
E11: 739 | F11: =DEMANDA_PREVISIÓN!E743 -> 37 | H11: 0 | I11: 150 | J11: 200 | L11: 20 | M11: 1200 | Y11: 11.003125 | Z11: 1
E12: 740 | F12: =DEMANDA_PREVISIÓN!E744 -> 35 | H12: 0 | I12: 150 | J12: 200 | L12: 20 | M12: 1200 | Y12: 11.012731
E13: 741 | F13: =DEMANDA_PREVISIÓN!E745 -> 37 | H13: 0 | I13: 150 | J13: 200 | L13: 20 | M13: 1200 | Y13: 11.022338
E14: 742 | F14: =DEMANDA_PREVISIÓN!E746 -> 31 | H14: 150 | J14: 200 | L14: 20 | M14: 1200 | Y14: 11.031944
E15: 743 | F15: =DEMANDA_PREVISIÓN!E747 -> 46 | H15: =H14-F15 -> 104 | J15: 200 | L15: 20 | M15: 1200 | Y15: 11.041551
E16: 744 | F16: =DEMANDA_PREVISIÓN!E748 -> 47 | H16: =H15-F16 -> 57 | J16: 200 | L16: 20 | M16: 1200 | Y16: 11.051157
E17: 745 | F17: =DEMANDA_PREVISIÓN!E749 -> 34 | H17: =H16-F17 -> 23 | I17: 200 | J17: 200 | L17: 20 | M17: 1200 | Y17: 11.060764
E18: 746 | F18: =DEMANDA_PREVISIÓN!E750 -> 41 | H18: 0 | I18: 200 | J18: 200 | L18: 200 | M18: 1200 | Y18: 11.07037
E19: 747 | F19: =DEMANDA_PREVISIÓN!E751 -> 40 | H19: 0 | I19: 200 | J19: 200 | L19: 200 | M19: 1200 | Y19: 11.079977
E20: 748 | F20: =DEMANDA_PREVISIÓN!E752 -> 28 | H20: 0 | I20: 200 | J20: 200 | L20: 200 | M20: 1200 | Y20: 11.089583
E21: 749 | F21: =DEMANDA_PREVISIÓN!E753 -> 42 | H21: 0 | I21: 200 | J21: 200 | L21: 200 | M21: 1200 | Y21: 11.09919
E22: 750 | F22: =DEMANDA_PREVISIÓN!E754 -> 32 | H22: 0 | I22: 200 | J22: 200 | L22: 200 | M22: 1200 | Y22: 11.108796
E23: 751 | F23: =DEMANDA_PREVISIÓN!E755 -> 48 | H23: 0 | I23: 200 | J23: 200 | L23: 200 | M23: 1200 | Y23: 11.118403
E24: 752 | F24: =DEMANDA_PREVISIÓN!E756 -> 31 | H24: 200 | J24: 200 | L24: 200 | M24: 1200 | Y24: 11.128009
E25: 753 | F25: =DEMANDA_PREVISIÓN!E757 -> 48 | H25: =H24-F25 -> 152 | J25: 200 | L25: 200 | M25: 1200 | Y25: 11.137616
E26: 754 | F26: =DEMANDA_PREVISIÓN!E758 -> 50 | H26: =H25-F26 -> 102 | J26: 200 | L26: 200 | M26: 1200 | Y26: 11.147222
E27: 755 | F27: =DEMANDA_PREVISIÓN!E759 -> 38 | H27: =H26-F27 -> 64 | I27: 200 | J27: 200 | L27: 200 | M27: 1200 | Y27: 11.156829
E28: 756 | F28: =DEMANDA_PREVISIÓN!E760 -> 31 | H28: =H27-F28 -> 33 | I28: 200 | J28: 200 | L28: 20 | M28: 1200 | Y28: 11.166435
E29: 757 | F29: =DEMANDA_PREVISIÓN!E761 -> 41 | H29: 0 | I29: 200 | J29: 200 | L29: 20 | M29: 1200 | Y29: 11.176042
E30: 758 | F30: =DEMANDA_PREVISIÓN!E762 -> 44 | H30: 0 | I30: 200 | J30: 200 | L30: 20 | M30: 1200 | Y30: 11.185648
E31: 759 | F31: =DEMANDA_PREVISIÓN!E763 -> 34 | H31: 0 | I31: 200 | J31: 200 | L31: 20 | M31: 1200 | Y31: 11.195255
E32: 760 | F32: =DEMANDA_PREVISIÓN!E764 -> 34 | H32: 0 | I32: 200 | J32: 200 | L32: 20 | M32: 1200 | Y32: 11.204861
E33: 761 | F33: =DEMANDA_PREVISIÓN!E765 -> 49 | H33: 0 | I33: 200 | J33: 200 | L33: 20 | M33: 1200 | Y33: 11.214468
D34: Febrero | E34: 762 | F34: =DEMANDA_PREVISIÓN!E766 -> 41 | H34: 200 | J34: 200 | L34: 20 | M34: 1200 | Y34: 11.224074
E35: 763 | F35: =DEMANDA_PREVISIÓN!E767 -> 40 | H35: =H34-F35 -> 160 | J35: 200 | L35: 20 | M35: 1200 | Y35: 11.233681
E36: 764 | F36: =DEMANDA_PREVISIÓN!E768 -> 46 | H36: =H35-F36 -> 114 | J36: 200 | L36: 20 | M36: 1200 | Y36: 11.243287
E37: 765 | F37: =DEMANDA_PREVISIÓN!E769 -> 31 | H37: =H36-F37 -> 83 | I37: 200 | J37: 200 | L37: 20 | M37: 1200 | Y37: 11.252894
E38: 766 | F38: =DEMANDA_PREVISIÓN!E770 -> 38 | H38: =H37-F38 -> 45 | I38: 200 | J38: 200 | L38: 20 | M38: 1200 | Y38: 11.2625
E39: 767 | F39: =DEMANDA_PREVISIÓN!E771 -> 39 | H39: =H38-F39 -> 6 | I39: 200 | J39: 200 | L39: 20 | M39: 1200 | Y39: 11.272106
E40: 768 | F40: =DEMANDA_PREVISIÓN!E772 -> 40 | H40: 0 | I40: 200 | J40: 200 | L40: 20 | M40: 1200 | Y40: 11.281713
E41: 769 | F41: =DEMANDA_PREVISIÓN!E773 -> 48 | H41: 0 | I41: 200 | J41: 200 | L41: 20 | M41: 1200 | Y41: 11.291319
E42: 770 | F42: =DEMANDA_PREVISIÓN!E774 -> 39 | H42: 0 | I42: 200 | J42: 200 | L42: 20 | M42: 1200 | Y42: 11.300926
E43: 771 | F43: =DEMANDA_PREVISIÓN!E775 -> 42 | H43: 0 | I43: 200 | J43: 200 | L43: 20 | M43: 1200 | Y43: 11.310532
E44: 772 | F44: =DEMANDA_PREVISIÓN!E776 -> 43 | H44: 200 | J44: 200 | L44: 20 | M44: 1200 | Y44: 11.320139
E45: 773 | F45: =DEMANDA_PREVISIÓN!E777 -> 48 | H45: =H44-F45 -> 152 | J45: 200 | L45: 20 | M45: 1200 | Y45: 11.329745
E46: 774 | F46: =DEMANDA_PREVISIÓN!E778 -> 45 | H46: =H45-F46 -> 107 | J46: 200 | L46: 20 | M46: 1200 | Y46: 11.339352
E47: 775 | F47: =DEMANDA_PREVISIÓN!E779 -> 53 | H47: =H46-F47 -> 54 | I47: 200 | J47: 200 | L47: 20 | M47: 1200 | Y47: 11.348958
E48: 776 | F48: =DEMANDA_PREVISIÓN!E780 -> 27 | H48: =H47-F48 -> 27 | I48: 200 | J48: 200 | L48: 20 | M48: 1200 | Y48: 11.358565
E49: 777 | F49: =DEMANDA_PREVISIÓN!E781 -> 38 | H49: 0 | I49: 200 | J49: 200 | L49: 20 | M49: 1200 | Y49: 11.368171
E50: 778 | F50: =DEMANDA_PREVISIÓN!E782 -> 40 | H50: 0 | I50: 200 | J50: 200 | L50: 20 | M50: 1200 | Y50: 11.377778
E51: 779 | F51: =DEMANDA_PREVISIÓN!E783 -> 38 | H51: 0 | I51: 200 | J51: 200 | L51: 20 | M51: 1200 | Y51: 11.387384
E52: 780 | F52: =DEMANDA_PREVISIÓN!E784 -> 40 | H52: 0 | I52: 200 | J52: 200 | L52: 20 | M52: 1200 | Y52: 11.396991
E53: 781 | F53: =DEMANDA_PREVISIÓN!E785 -> 36 | H53: 0 | I53: 200 | J53: 200 | L53: 20 | M53: 1200 | Y53: 11.406597
E54: 782 | F54: =DEMANDA_PREVISIÓN!E786 -> 45 | H54: 200 | J54: 200 | L54: 20 | M54: 1200 | Y54: 11.416204
E55: 783 | F55: =DEMANDA_PREVISIÓN!E787 -> 38 | H55: =H54-F55 -> 162 | J55: 200 | L55: 20 | M55: 1200 | Y55: 11.42581
E56: 784 | F56: =DEMANDA_PREVISIÓN!E788 -> 36 | H56: =H55-F56 -> 126 | J56: 200 | L56: 20 | M56: 1200 | Y56: 11.435417
E57: 785 | F57: =DEMANDA_PREVISIÓN!E789 -> 51 | H57: =H56-F57 -> 75 | I57: 200 | J57: 200 | L57: 20 | M57: 1200 | Y57: 11.445023
E58: 786 | F58: =DEMANDA_PREVISIÓN!E790 -> 45 | H58: =H57-F58 -> 30 | I58: 200 | J58: 200 | L58: 20 | M58: 1200 | Y58: 11.45463
E59: 787 | F59: =DEMANDA_PREVISIÓN!E791 -> 36 | H59: 0 | I59: 200 | J59: 200 | L59: 20 | M59: 1200 | Y59: 11.464236
E60: 788 | F60: =DEMANDA_PREVISIÓN!E792 -> 40 | H60: 0 | I60: 200 | J60: 200 | L60: 20 | M60: 1200 | Y60: 11.473843
E61: 789 | F61: =DEMANDA_PREVISIÓN!E793 -> 42 | H61: 0 | I61: 200 | J61: 200 | L61: 20 | M61: 1200 | Y61: 11.483449
D62: Marzo | E62: 790 | F62: =DEMANDA_PREVISIÓN!E794 -> 39 | H62: 0 | I62: 200 | J62: 200 | L62: 20 | M62: 1200 | Y62: 11.493056
E63: 791 | F63: =DEMANDA_PREVISIÓN!E795 -> 37 | H63: 0 | I63: 200 | J63: 200 | L63: 20 | M63: 1200 | Y63: 11.502662
E64: 792 | F64: =DEMANDA_PREVISIÓN!E796 -> 35 | H64: 200 | J64: 200 | L64: 20 | M64: 1200 | Y64: 11.512269
E65: 793 | F65: =DEMANDA_PREVISIÓN!E797 -> 39 | H65: =H64-F65 -> 161 | J65: 200 | L65: 20 | M65: 1200 | Y65: 11.521875
E66: 794 | F66: =DEMANDA_PREVISIÓN!E798 -> 39 | H66: =H65-F66 -> 122 | J66: 200 | L66: 20 | M66: 1200 | Y66: 11.531481
E67: 795 | F67: =DEMANDA_PREVISIÓN!E799 -> 45 | H67: =H66-F67 -> 77 | I67: 200 | J67: 200 | L67: 20 | M67: 1200 | Y67: 11.541088
E68: 796 | F68: =DEMANDA_PREVISIÓN!E800 -> 34 | H68: =H67-F68 -> 43 | I68: 200 | J68: 200 | L68: 20 | M68: 1200 | Y68: 11.550694
E69: 797 | F69: =DEMANDA_PREVISIÓN!E801 -> 51 | H69: 0 | I69: 200 | J69: 200 | L69: 20 | M69: 1200 | Y69: 11.560301
E70: 798 | F70: =DEMANDA_PREVISIÓN!E802 -> 36 | H70: 0 | I70: 200 | J70: 200 | L70: 20 | M70: 1200 | Y70: 11.569907
E71: 799 | F71: =DEMANDA_PREVISIÓN!E803 -> 37 | H71: 0 | I71: 200 | J71: 200 | L71: 20 | M71: 1200 | Y71: 11.579514
E72: 800 | F72: =DEMANDA_PREVISIÓN!E804 -> 47 | H72: 0 | I72: 200 | J72: 200 | L72: 20 | M72: 1200 | Y72: 11.58912
E73: 801 | F73: =DEMANDA_PREVISIÓN!E805 -> 41 | H73: 0 | I73: 200 | J73: 200 | L73: 20 | M73: 1200 | Y73: 11.598727
E74: 802 | F74: =DEMANDA_PREVISIÓN!E806 -> 41 | H74: 200 | J74: 200 | L74: 20 | M74: 1200 | Y74: 11.608333
E75: 803 | F75: =DEMANDA_PREVISIÓN!E807 -> 42 | H75: =H74-F75 -> 158 | J75: 200 | L75: 20 | M75: 1200 | Y75: 11.61794
E76: 804 | F76: =DEMANDA_PREVISIÓN!E808 -> 48 | H76: =H75-F76 -> 110 | J76: 200 | L76: 20 | M76: 1200 | Y76: 11.627546
E77: 805 | F77: =DEMANDA_PREVISIÓN!E809 -> 55 | H77: =H76-F77 -> 55 | I77: 200 | J77: 200 | L77: 20 | M77: 1200 | Y77: 11.637153
E78: 806 | F78: =DEMANDA_PREVISIÓN!E810 -> 50 | H78: =H77-F78 -> 5 | I78: 200 | J78: 200 | L78: 20 | M78: 1200 | Y78: 11.646759
E79: 807 | F79: =DEMANDA_PREVISIÓN!E811 -> 44 | H79: 0 | I79: 200 | J79: 200 | L79: 20 | M79: 1200 | Y79: 11.656366
E80: 808 | F80: =DEMANDA_PREVISIÓN!E812 -> 41 | H80: 0 | I80: 200 | J80: 200 | L80: 20 | M80: 1200 | Y80: 11.665972
E81: 809 | F81: =DEMANDA_PREVISIÓN!E813 -> 38 | H81: 0 | I81: 200 | J81: 200 | L81: 20 | M81: 1200 | Y81: 11.675579
E82: 810 | F82: =DEMANDA_PREVISIÓN!E814 -> 44 | H82: 0 | I82: 200 | J82: 200 | L82: 20 | M82: 1200 | Y82: 11.685185
E83: 811 | F83: =DEMANDA_PREVISIÓN!E815 -> 39 | H83: 0 | I83: 200 | J83: 200 | L83: 20 | M83: 1200 | Y83: 11.694792
E84: 812 | F84: =DEMANDA_PREVISIÓN!E816 -> 52 | H84: 200 | J84: 200 | L84: 20 | M84: 1200 | Y84: 11.704398
E85: 813 | F85: =DEMANDA_PREVISIÓN!E817 -> 47 | H85: =H84-F85 -> 153 | J85: 200 | L85: 20 | M85: 1200 | Y85: 11.714005
E86: 814 | F86: =DEMANDA_PREVISIÓN!E818 -> 43 | H86: =H85-F86 -> 110 | J86: 200 | L86: 20 | M86: 1200 | Y86: 11.723611
E87: 815 | F87: =DEMANDA_PREVISIÓN!E819 -> 56 | H87: =H86-F87 -> 54 | I87: 200 | J87: 200 | L87: 20 | M87: 1200 | Y87: 11.733218
E88: 816 | F88: =DEMANDA_PREVISIÓN!E820 -> 45 | H88: =H87-F88 -> 9 | I88: 200 | J88: 200 | L88: 20 | M88: 1200 | Y88: 11.742824
E89: 817 | F89: =DEMANDA_PREVISIÓN!E821 -> 49 | H89: 0 | I89: 200 | J89: 200 | L89: 20 | M89: 1200 | Y89: 11.752431
E90: 818 | F90: =DEMANDA_PREVISIÓN!E822 -> 43 | H90: 0 | I90: 200 | J90: 200 | L90: 20 | M90: 1200 | Y90: 11.762037
E91: 819 | F91: =DEMANDA_PREVISIÓN!E823 -> 47 | H91: 0 | I91: 200 | J91: 200 | L91: 20 | M91: 1200 | Y91: 11.771644
E92: 820 | F92: =DEMANDA_PREVISIÓN!E824 -> 44 | H92: 0 | I92: 200 | J92: 200 | L92: 20 | M92: 1200 | Y92: 11.78125
C93: II | D93: Abril | E93: 821 | F93: =DEMANDA_PREVISIÓN!E825 -> 42 | H93: 0 | I93: 200 | J93: 200 | L93: 20 | M93: 1200 | Y93: 11.790856
E94: 822 | F94: =DEMANDA_PREVISIÓN!E826 -> 49 | H94: =I93 -> 200 | J94: 200 | L94: 20 | M94: 1200 | Y94: 11.800463
E95: 823 | F95: =DEMANDA_PREVISIÓN!E827 -> 43 | H95: =H94-F95 -> 157 | J95: 200 | L95: 20 | M95: 1200 | Y95: 11.810069
E96: 824 | F96: =DEMANDA_PREVISIÓN!E828 -> 29 | H96: =H95-F96 -> 128 | J96: 200 | L96: 20 | M96: 1200 | Y96: 11.819676
E97: 825 | F97: =DEMANDA_PREVISIÓN!E829 -> 32 | H97: =H96-F97 -> 96 | I97: 200 | J97: 200 | L97: 20 | M97: 1200 | Y97: 11.829282
E98: 826 | F98: =DEMANDA_PREVISIÓN!E830 -> 36 | H98: =H97-F98 -> 60 | I98: 200 | J98: 400 | L98: 50 | M98: 1200 | Y98: 11.838889
E99: 827 | F99: =DEMANDA_PREVISIÓN!E831 -> 51 | H99: =H98-F99 -> 9 | I99: 200 | J99: 400 | L99: 50 | M99: 1200 | Y99: 11.848495
E100: 828 | F100: =DEMANDA_PREVISIÓN!E832 -> 44 | H100: 0 | I100: 200 | J100: 400 | L100: 50 | M100: 1200 | Y100: 11.858102
...

Sheet DEMANDA_PREVISIÓN
B2: DEMANDA | H2: GRÁFICO DE LA DEMANDA
B4: DÍA | C4: FECHA | D4: HISTÓRICO | E4: PREVISIÓN
B5: 1 | C5: 45658 | D5: 12
B6: 2 | C6: 45659 | D6: 40
B7: 3 | C7: 45660 | D7: 45
B8: 4 | C8: 45661 | D8: 34
B9: 5 | C9: 45662 | D9: 37
B10: 6 | C10: 45663 | D10: 45
B11: 7 | C11: 45664 | D11: 38
B12: 8 | C12: 45665 | D12: 32
B13: 9 | C13: 45666 | D13: 33
B14: 10 | C14: 45667 | D14: 40
B15: 11 | C15: 45668 | D15: 36
B16: 12 | C16: 45669 | D16: 44
... B43: 39 | C43: 45696 | D43: 45
B44: 40 | C44: 45697 | D44: 40 | H44: Etiquetas de fila | I44: Suma de HISTÓRICO | J44: Suma de PREVISIÓN | M44: AÑO | N44: TRIMESTRE | O44: DEMANDA
B45: 41 | C45: 45698 | D45: 37 | H45: 2025 | M45: 1 | N45: I | O45: =SUM(I46:I48) -> 3821
B46: 42 | C46: 45699 | D46: 52 | H46: Ene | I46: 1221 | N46: II | O46: =SUM(I49:I51) -> 3821
B47: 43 | C47: 45700 | D47: 43 | H47: Feb | I47: 1219 | N47: III | O47: =SUM(I52:I54) -> 3290
B48: 44 | C48: 45701 | D48: 42 | H48: Mar | I48: 1381 | N48: IV | O48: =SUM(I55:I57) -> 3326
B49: 45 | C49: 45702 | D49: 52 | H49: Abr | I49: 1318 | M49: 2 | N49: I | O49: =SUM(I59:I61) -> 3809
B50: 46 | C50: 45703 | D50: 41 | H50: May | I50: 1353 | N50: II | O50: =SUM(I62:I64) -> 3888
B51: 47 | C51: 45704 | D51: 43 | H51: Jun | I51: 1150 | N51: III | O51: =SUM(I65:I67) -> 3111
B52: 48 | C52: 45705 | D52: 45 | H52: Jul | I52: 1173 | K52: =SUM(I46:I51) -> 7642 | N52: IV | O52: =SUM(I68:I70) -> 3222
B53: 49 | C53: 45706 | D53: 30 | H53: Ago | I53: 1150 | M53: 3 | N53: I | O53: =SUM(J72:J74) -> 3736
B54: 50 | C54: 45707 | D54: 40 | H54: Set | I54: 967 | N54: II | O54: =SUM(J75:J77) -> 3820
B55: 51 | C55: 45708 | D55: 35 | H55: Oct | I55: 1084 | N55: III | O55: =SUM(J78:J80) -> 3136
B56: 52 | C56: 45709 | D56: 53 | H56: Nov | I56: 1088 | N56: IV | O56: =SUM(J81:J83) -> 3241
B57: 53 | C57: 45710 | D57: 44 | H57: Dic | I57: 1154 | M57: 4 | N57: I | O57: =SUM(J85:J87) -> 3842
B58: 54 | C58: 45711 | D58: 40 | H58: 2026 | N58: II | O58: =SUM(J88:J90) -> 3884
B59: 55 | C59: 45712 | D59: 48 | H59: Ene | I59: 1248 | K59: =SUM(I46:I51,I59:I64,J72:J77,J85:J90)/4 -> 7655.25 | N59: III | O59: =SUM(J91:J93) -> 3206
B60: 56 | C60: 45713 | D60: 46 | H60: Feb | I60: 1174 | N60: IV | O60: =SUM(J94:J96) -> 3271
B61: 57 | C61: 45714 | D61: 41 | H61: Mar | I61: 1387
B62: 58 | C62: 45715 | D62: 48 | H62: Abr | I62: 1331
B63: 59 | C63: 45716 | D63: 51 | H63: May | I63: 1322
B64: 60 | C64: 45717 | D64: 47 | H64: Jun | I64: 1235
B65: 61 | C65: 45718 | D65: 45 | H65: Jul | I65: 1144
B66: 62 | C66: 45719 | D66: 34 | H66: Ago | I66: 1046
B67: 63 | C67: 45720 | D67: 37 | H67: Set | I67: 921
B68: 64 | C68: 45721 | D68: 34 | H68: Oct | I68: 1028
B69: 65 | C69: 45722 | D69: 49 | H69: Nov | I69: 1084
B70: 66 | C70: 45723 | D70: 39 | H70: Dic | I70: 1110 | L70: 160 | N70: 80 | P70: 90 | R70: 80-
B71: 67 | C71: 45724 | D71: 61 | H71: 2027 | L71: 10 | P71: 70
B72: 68 | C72: 45725 | D72: 55 | H72: Ene | J72: 1243 | S72: MESES
B73: 69 | C73: 45726 | D73: 53 | H73: Feb | J73: 1145
B74: 70 | C74: 45727 | D74: 30 | H74: Mar | J74: 1348 | M74: ACTUAL | N74: 20 | P74: 30 | R74: =N74*P74 -> 600
B75: 71 | C75: 45728 | D75: 50 | H75: Abr | J75: 1302 | U75: =13.63 -> 13.63 | V75: MINUTOS | W75: APROX
B76: 72 | C76: 45729 | D76: 44 | H76: May | J76: 1306 | N76: 50 | P76: 30 | R76: =N76*P76 -> 1500 | V76: CAMBIAR LOS PUNTOS DE REORDEN
B77: 73 | C77: 45730 | D77: 40 | H77: Jun | J77: 1212 | V77: PARA LLEGAR AL INVENTARIO DESEADO
B78: 74 | C78: 45731 | D78: 44 | H78: Jul | J78: 1134 | V78: 14 MINUTOS PARA PASARLO A DÍAS
B79: 75 | C79: 45732 | D79: 51 | H79: Ago | J79: 1075
B80: 76 | C80: 45733 | D80: 46 | H80: Set | J80: 927
B81: 77 | C81: 45734 | D81: 41 | H81: Oct | J81: 1038
B82: 78 | C82: 45735 | D82: 43 | H82: Nov | J82: 1076
B83: 79 | C83: 45736 | D83: 59 | H83: Dic | J83: 1127
B84: 80 | C84: 45737 | D84: 45 | H84: 2028
B85: 81 | C85: 45738 | D85: 33 | H85: Ene | J85: 1265
B86: 82 | C86: 45739 | D86: 42 | H86: Feb | J86: 1204
B87: 83 | C87: 45740 | D87: 40 | H87: Mar | J87: 1373
B88: 84 | C88: 45741 | D88: 47 | H88: Abr | J88: 1332
B89: 85 | C89: 45742 | D89: 53 | H89: May | J89: 1316
B90: 86 | C90: 45743 | D90: 44 | H90: Jun | J90: 1236
B91: 87 | C91: 45744 | D91: 42 | H91: Jul | J91: 1146
B92: 88 | C92: 45745 | D92: 38 | H92: Ago | J92: 1096
B93: 89 | C93: 45746 | D93: 51 | H93: Set | J93: 964
B94: 90 | C94: 45747 | D94: 44 | H94: Oct | J94: 1049
B95: 91 | C95: 45748 | D95: 32 | H95: Nov | J95: 1110
B96: 92 | C96: 45749 | D96: 34 | H96: Dic | J96: 1112
B97: 93 | C97: 45750 | D97: 50 | H97: Total general | I97: 28288 | J97: 28136
B98: 94 | C98: 45751 | D98: 47
B99: 95 | C99: 45752 | D99: 43
B100: 96 | C100: 45753 | D100: 37
B101: 97 | C101: 45754 | D101: 41
B102: 98 | C102: 45755 | D102: 36
B103: 99 | C103: 45756 | D103: 52
B104: 100 | C104: 45757 | D104: 53
B105: 101 | C105: 45758 | D105: 43
B106: 102 | C106: 45759 | D106: 30
B107: 103 | C107: 45760 | D107: 47
B108: 104 | C108: 45761 | D108: 43
B109: 105 | C109: 45762 | D109: 49
... B734: 730 | C734: 46387 | D734: 24
B735: 731 | C735: 46388 | E735: =ROUNDUP(_xlfn.FORECAST.ETS(B735,$D$5:$D$734,$B$5:$B$734,365,0,1),0) -> 44
B736: 732 | C736: 46389 | E736: =ROUNDUP(_xlfn.FORECAST.ETS(B736,$D$5:$D$734,$B$5:$B$734,365,0,1),0) -> 41
B737: 733 | C737: 46390 | E737: =ROUNDUP(_xlfn.FORECAST.ETS(B737,$D$5:$D$734,$B$5:$B$734,365,0,1),0) -> 41
B738: 734 | C738: 46391 | E738: =ROUNDUP(_xlfn.FORECAST.ETS(B738,$D$5:$D$734,$B$5:$B$734,365,0,1),0) -> 54
B739: 735 | C739: 46392 | E739: =ROUNDUP(_xlfn.FORECAST.ETS(B739,$D$5:$D$734,$B$5:$B$734,365,0,1),0) -> 40
B740: 736 | C740: 46393 | E740: =ROUNDUP(_xlfn.FORECAST.ETS(B740,$D$5:$D$734,$B$5:$B$734,365,0,1),0) -> 46
B741: 737 | C741: 46394 | E741: =ROUNDUP(_xlfn.FORECAST.ETS(B741,$D$5:$D$734,$B$5:$B$734,365,0,1),0) -> 33
B742: 738 | C742: 46395 | E742: =ROUNDUP(_xlfn.FORECAST.ETS(B742,$D$5:$D$734,$B$5:$B$734,365,0,1),0) -> 46
B743: 739 | C743: 46396 | E743: =ROUNDUP(_xlfn.FORECAST.ETS(B743,$D$5:$D$734,$B$5:$B$734,365,0,1),0) -> 37
B744: 740 | C744: 46397 | E744: =ROUNDUP(_xlfn.FORECAST.ETS(B744,$D$5:$D$734,$B$5:$B$734,365,0,1),0) -> 35
B745: 741 | C745: 46398 | E745: =ROUNDUP(_xlfn.FORECAST.ETS(B745,$D$5:$D$734,$B$5:$B$734,365,0,1),0) -> 37
B746: 742 | C746: 46399 | E746: =ROUNDUP(_xlfn.FORECAST.ETS(B746,$D$5:$D$734,$B$5:$B$734,365,0,1),0) -> 31
... B1464: 1460 | C1464: 47117 | E1464: =ROUNDUP(_xlfn.FORECAST.ETS(B1464,$D$5:$D$734,$B$5:$B$734,365,0,1),0) -> 28

Sheet EOQ_PREVISIÓN
B2: ANÁLISIS DE CANTIDAD ECONÓMICA DE PEDIDO
B4: AÑO | C4: 3 | G4: 4
B5: TRIMESTRE | C5: I | D5: II | E5: III | F5: IV | G5: I | H5: II | I5: III | J5: IV
B6: COSTO UNITARIO | C6: 1000 | D6: 1000 | E6: 1000 | F6: 1000 | G6: 1000 | H6: 1000 | I6: 1000 | J6: 1000
B7: COSTO DE PREPARACIÓN | C7: 1500 | D7: 1500 | E7: 1500 | F7: 1500 | G7: 1500 | H7: 1500 | I7: 1500 | J7: 1500
B8: DEMANDA | C8: =DEMANDA_PREVISIÓN!O53 -> 3736 | D8: =DEMANDA_PREVISIÓN!O54 -> 3820 | E8: =DEMANDA_PREVISIÓN!O55 -> 3136 | F8: =DEMANDA_PREVISIÓN!O56 -> 3241 | G8: =DEMANDA_PREVISIÓN!O57 -> 3842 | H8: =DEMANDA_PREVISIÓN!O58 -> 3884 | I8: =DEMANDA_PREVISIÓN!O59 -> 3206 | J8: =DEMANDA_PREVISIÓN!O60 -> 3271
B9: COSTO DE MANTENIMIENTO | C9: 100 | D9: 100 | E9: 100 | F9: 100 | G9: 100 | H9: 100 | I9: 100 | J9: 100
B11: EOQ | C11: =SQRT((2*C7*C8)/C9) -> 334.78351 | D11: =SQRT((2*D7*D8)/D9) -> 338.52622 | E11: =SQRT((2*E7*E8)/E9) -> 306.72463 | F11: =SQRT((2*F7*F8)/F9) -> 311.81725 | G11: =SQRT((2*G7*G8)/G9) -> 339.49963 | H11: =SQRT((2*H7*H8)/H9) -> 341.35026 | I11: =SQRT((2*I7*I8)/I9) -> 310.12901 | J11: =SQRT((2*J7*J8)/J9) -> 313.25708
B16: AÑO | C16: 3 | G16: 4
B17: TRIMESTRE | C17: I | D17: II | E17: III | F17: IV | G17: I | H17: II | I17: III | J17: IV
B18: DEMANDA (Bidones) | C18: =C8 -> 3736 | D18: =D8 -> 3820 | E18: =E8 -> 3136 | F18: =F8 -> 3241 | G18: =G8 -> 3842 | H18: =H8 -> 3884 | I18: =I8 -> 3206 | J18: =J8 -> 3271
B19: EOQ (Bidones) | C19: =C11 -> 334.78351 | D19: =D11 -> 338.52622 | E19: =E11 -> 306.72463 | F19: =F11 -> 311.81725 | G19: =G11 -> 339.49963 | H19: =H11 -> 341.35026 | I19: =I11 -> 310.12901 | J19: =J11 -> 313.25708
C20: 400 | D20: 400 | E20: 200 | F20: 200 | G20: 400 | H20: 400 | I20: 200 | J20: 200
C24: CANTIDAD | D24: COSTO POR LOTE | E24: COSTO UNITARIO | F24: PENDIENTE
C25: 50 | D25: =$C$7+$C$6*C25 -> 51500 | E25: =D25/C25 -> 1030 | F25: 0
C26: 100 | D26: =$C$7+$C$6*C26 -> 101500 | E26: =D26/C26 -> 1015 | F26: =ABS((E26-E25)/(C26-C25)) -> 0.3
C27: 150 | D27: =$C$7+$C$6*C27 -> 151500 | E27: =D27/C27 -> 1010 | F27: =ABS((E27-E26)/(C27-C26)) -> 0.1
C28: 200 | D28: =$C$7+$C$6*C28 -> 201500 | E28: =D28/C28 -> 1007.5 | F28: =ABS((E28-E27)/(C28-C27)) -> 0.05
C29: 250 | D29: =$C$7+$C$6*C29 -> 251500 | E29: =D29/C29 -> 1006 | F29: =ABS((E29-E28)/(C29-C28)) -> 0.03
C30: 300 | D30: =$C$7+$C$6*C30 -> 301500 | E30: =D30/C30 -> 1005 | F30: =ABS((E30-E29)/(C30-C29)) -> 0.02
C31: 350 | D31: =$C$7+$C$6*C31 -> 351500 | E31: =D31/C31 -> 1004.2857 | F31: =ABS((E31-E30)/(C31-C30)) -> 0.014285714
C32: 400 | D32: =$C$7+$C$6*C32 -> 401500 | E32: =D32/C32 -> 1003.75 | F32: =ABS((E32-E31)/(C32-C31)) -> 0.010714286
C33: 450 | D33: =$C$7+$C$6*C33 -> 451500 | E33: =D33/C33 -> 1003.3333 | F33: =ABS((E33-E32)/(C33-C32)) -> 0.0083333333
C34: 500 | D34: =$C$7+$C$6*C34 -> 501500 | E34: =D34/C34 -> 1003 | F34: =ABS((E34-E33)/(C34-C33)) -> 0.0066666667
C35: 550 | D35: =$C$7+$C$6*C35 -> 551500 | E35: =D35/C35 -> 1002.7273 | F35: =ABS((E35-E34)/(C35-C34)) -> 0.0054545455
C36: 600 | D36: =$C$7+$C$6*C36 -> 601500 | E36: =D36/C36 -> 1002.5 | F36: =ABS((E36-E35)/(C36-C35)) -> 0.0045454545
C37: 650 | D37: =$C$7+$C$6*C37 -> 651500 | E37: =D37/C37 -> 1002.3077 | F37: =ABS((E37-E36)/(C37-C36)) -> 0.0038461538
... C44: 1000 | D44: =$C$7+$C$6*C44 -> 1001500 | E44: =D44/C44 -> 1001.5 | F44: =ABS((E44-E43)/(C44-C43)) -> 0.0015789474

Sheet ROP_PREVISIÓN
C5: AÑO | D5: TRIMESTRE | E5: m | F5: LT | G5: K | H5: s | I5: ROP
C6: 3 | D6: I | E6: =DEMANDA_PREVISIÓN!O45/90 -> 42.455556 | F6: 17 | G6: 3.719 | H6: =_xlfn.STDEV.S(DEMANDA_PREVISIÓN!E735:E824) -> 6.1612133 | I6: =E6*F6+G6*H6*SQRT(F6) -> 816.21944
D7: II | E7: =DEMANDA_PREVISIÓN!O46/90 -> 42.455556 | F7: 15 | G7: 3.719 | H7: =_xlfn.STDEV.S(DEMANDA_PREVISIÓN!E826:E915) -> 5.8405359 | I7: =E7*F7+G7*H7*SQRT(F7) -> 720.95822
D8: III | E8: =DEMANDA_PREVISIÓN!O47/90 -> 36.555556 | F8: 11 | G8: 3.719 | H8: =_xlfn.STDEV.S(DEMANDA_PREVISIÓN!E916:E1005) -> 5.810963 | I8: =E8*F8+G8*H8*SQRT(F8) -> 473.78659
D9: IV | E9: =DEMANDA_PREVISIÓN!O48/90 -> 36.955556 | F9: 11 | G9: 3.719 | H9: =_xlfn.STDEV.S(DEMANDA_PREVISIÓN!E1006:E1095) -> 4.9438293 | I9: =E9*F9+G9*H9*SQRT(F9) -> 467.49091
C10: 4 | D10: I | E10: =DEMANDA_PREVISIÓN!O49/90 -> 42.322222 | F10: 15 | G10: 3.719 | H10: =_xlfn.STDEV.S(DEMANDA_PREVISIÓN!E1096:E1185) -> 6.391171 | I10: =E10*F10+G10*H10*SQRT(F10) -> 726.88936
D11: II | E11: =DEMANDA_PREVISIÓN!O50/90 -> 43.2 | F11: 15 | G11: 3.719 | H11: =_xlfn.STDEV.S(DEMANDA_PREVISIÓN!E1186:E1275) -> 5.8798732 | I11: =E11*F11+G11*H11*SQRT(F11) -> 732.69149
D12: III | E12: =DEMANDA_PREVISIÓN!O51/90 -> 34.566667 | F12: 11 | G12: 3.719 | H12: =_xlfn.STDEV.S(DEMANDA_PREVISIÓN!E1276:E1365) -> 5.852206 | I12: =E12*F12+G12*H12*SQRT(F12) -> 452.41753
D13: IV | E13: =DEMANDA_PREVISIÓN!O52/90 -> 35.8 | F13: 11 | G13: 3.719 | H13: =_xlfn.STDEV.S(DEMANDA_PREVISIÓN!E1366:E1455) -> 5.0770468 | I13: =E13*F13+G13*H13*SQRT(F13) -> 456.42297
C17: AÑO | D17: AÑO 3 | H17: AÑO 4
C18: TRIMESTRE | D18: I | E18: II | F18: III | G18: IV | H18: I | I18: II | J18: III | K18: IV
C19: EOQ (Bidones) | D19: 400 | E19: 400 | F19: 200 | G19: 200 | H19: 400 | I19: 400 | J19: 200 | K19: 200
C20: ROP (Bidones) | D20: =E6*F6+G6*H6 -> 744.658 | E20: =E7*F7+G7*H7 -> 658.55429 | F20: =E8*F8+G8*H8 -> 423.72208 | G20: =E9*F9+G9*H9 -> 424.89721 | H20: =E10*F10+G10*H10 -> 658.6021 | I20: =E11*F11+G11*H11 -> 669.86725 | J20: =E12*F12+G12*H12 -> 401.99769 | K20: =E13*F13+G13*H13 -> 412.68154
C21: ROP Redondeo | D21: 700 | E21: 700 | F21: 450 | G21: 450 | H21: 700 | I21: 700 | J21: 450 | K21: 450
E735: =ROP_PREVISIÓN!R12 -> 0

Sheet TRANSPORTE_PREVISIÓN
B2: ANÁLISIS DE TRANSPORTE
B4: TRANSPORTE | C4: COSTO | D4: BIDONES | E4: COSTO UNITARIO | F4: TIEMPO DE ENVÍO (Días)
B5: Camión | C5: $15.000,00 | D5: 200 | E5: 75 | F5: 7
D6: 150 | E6: 100
D7: 100 | E7: 150
D8: 50 | E8: 300
B9: Correo | C9: $150,00 | D9: 1 | E9: 150 | F9: 1
D17: =15000/200 -> 75

Sheet CAPACIDAD_PREVISIÓN
B2: ANÁLISIS DE CAPACIDAD | J2: 400
B4: DEMANDA ANUAL (Bidones) | C4: CAPACIDAD (Bidones/Día) | D4: PRODUCCIÓN ANUAL (Bidones) | E4: DEMANDA EN LOS TRIMESTRES I - II (SEMESTRE) (Bidones) | F4: PRODUCCIÓN CADA 2 TRIMESTRES (Bidones) | G4: COSTO POR AUMENTAR CAPACIDAD | H4: SALDO FINAL
B5: =AVERAGE(DEMANDA_PREVISIÓN!M46:AB46) -> 3821 | C5: 20 | D5: =C5*365 -> 7300 | E5: =(SUM(DEMANDA_PREVISIÓN!O45:O46)+SUM(DEMANDA_PREVISIÓN!O49:O50)+SUM(DEMANDA_PREVISIÓN!O53:O54)+SUM(DEMANDA_PREVISIÓN!O57:O58))/4 -> 7655.25 | F5: =C5*180 -> 3600 | G5: - | H5: =3142*1000 -> 3142000
C6: 25 | D6: =C6*365 -> 9125 | F6: =C6*180 -> 4500 | G6: =(C6-$C$5)*50000 -> 250000 | H6: =$H$5-G6 -> 2892000 | J6: e | K6: 120 | L6: =20*31 -> 620 | M6: =K6-L6 -> -500 | N6: =21*20 -> 420 | P6: Revisae inventario | R6: 10000 LOTE | S6: 50 CAPACIDAD
C7: 30 | D7: =C7*365 -> 10950 | F7: =C7*180 -> 5400 | G7: =(C7-$C$5)*50000 -> 500000 | H7: =$H$5-G7 -> 2642000 | J7: f | K7: 247 | L7: =20*31 -> 620 | M7: 20 | P7: 9DIAS
C8: 35 | D8: =C8*365 -> 12775 | F8: =C8*180 -> 6300 | G8: =(C8-$C$5)*50000 -> 750000 | H8: =$H$5-G8 -> 2392000 | J8: m | K8: 473 | L8: =20*31 -> 620 | M8: 30
C9: 40 | D9: =C9*365 -> 14600 | F9: =C9*180 -> 7200 | G9: =(C9-$C$5)*50000 -> 1000000 | H9: =$H$5-G9 -> 2142000 | L9: =50*30 -> 1500
C10: 45 | D10: =C10*365 -> 16425 | F10: =C10*180 -> 8100 | G10: =(C10-$C$5)*50000 -> 1250000 | H10: =$H$5-G10 -> 1892000 | J10: =F10-E5 -> 444.75 | L10: =50*30 -> 1500
C11: 50 | D11: =C11*365 -> 18250 | F11: =C11*180 -> 9000 | G11: =(C11-$C$5)*50000 -> 1500000 | H11: =$H$5-G11 -> 1642000 | J11: =F11-E6 -> 9000 | L11: =50*30 -> 1500
C12: 55 | D12: =C12*365 -> 20075 | F12: =C12*180 -> 9900 | G12: =(C12-$C$5)*50000 -> 1750000 | H12: =$H$5-G12 -> 1392000 | J12: =F12-E7 -> 9900 | L12: =50*30 -> 1500
C13: 60 | D13: =C13*365 -> 21900 | F13: =C13*180 -> 10800 | G13: =(C13-$C$5)*50000 -> 2000000 | H13: =$H$5-G13 -> 1142000 | J13: =F13-E8 -> 10800 | L13: =50*30 -> 1500
L14: =50*30 -> 1500
L15: =50*30 -> 1500
L16: =50*30 -> 1500
L17: =50*30 -> 1500
K18: =H11 -> 1642000

Sheet PROYECCIÓN_PREVISIÓN_EDITAR (O)
B4: AÑO | C4: TRIMESTRE | D4: MES | E4: DIA | F4: DEMANDA | H4: ALMACEN | I4: CAMION | J4: EN PROCESO | L4: CAPACIDAD | M4: ROP | Q4: HORA | R4: DÍA
B5: - | C5: - | D5: - | E5: 730 | F5: =PRUEBA_HISTÓRICO!F734 -> 24 | H5: 0 | I5: 150 | J5: 150 | L5: 20 | M5: 800 | Q5: 10.916667 | R5: 1
B6: 2027 | C6: I | D6: Enero | E6: 731 | F6: =DEMANDA_PREVISIÓN!E735 -> 44 | H6: 0 | I6: 150 | J6: 150 | L6: 20 | M6: 800 | Q6: 10.926273
E7: 732 | F7: =DEMANDA_PREVISIÓN!E736 -> 41 | H7: 0 | I7: 150 | J7: 150 | L7: 20 | M7: 800 | Q7: 10.93588
E8: 733 | F8: =DEMANDA_PREVISIÓN!E737 -> 41 | H8: 0 | I8: 150 | J8: 150 | L8: 20 | M8: 800 | Q8: 10.945486
E9: 734 | F9: =DEMANDA_PREVISIÓN!E738 -> 54 | H9: 150 | J9: 150 | L9: 20 | M9: 800 | Q9: 10.955093
E10: 735 | F10: =DEMANDA_PREVISIÓN!E739 -> 40 | H10: =H9-F10 -> 110 | I10: 150 | J10: 150 | L10: 20 | M10: 800 | Q10: 10.964699
E11: 736 | F11: =DEMANDA_PREVISIÓN!E740 -> 46 | H11: =H10-F11 -> 64 | I11: 150 | J11: 200 | L11: 20 | M11: 800 | N11: =J11/L11 -> 10 | O11: =1500+200*1000 -> 201500 | Q11: 10.974306
E12: 737 | F12: =DEMANDA_PREVISIÓN!E741 -> 33 | H12: =H11-F12 -> 31 | I12: 150 | J12: 200 | L12: 20 | M12: 800 | N12: =J12/L12 -> 10 | Q12: 10.983912
E13: 738 | F13: =DEMANDA_PREVISIÓN!E742 -> 46 | H13: 0 | I13: 150 | J13: 200 | L13: 20 | M13: 800 | N13: =J13/L13 -> 10 | Q13: 10.993519
E14: 739 | F14: =DEMANDA_PREVISIÓN!E743 -> 37 | H14: 0 | I14: 150 | J14: 200 | L14: 20 | M14: 800 | N14: =J14/L14 -> 10 | P14: costo de produccion | Q14: 11.003125 | R14: 2
E15: 740 | F15: =DEMANDA_PREVISIÓN!E744 -> 35 | H15: 0 | I15: 150 | J15: 200 | L15: 20 | M15: 800 | N15: =J15/L15 -> 10 | Q15: 11.012731
E16: 741 | F16: =DEMANDA_PREVISIÓN!E745 -> 37 | H16: 0 | I16: 150 | J16: 200 | L16: 20 | M16: 800 | N16: =J16/L16 -> 10 | O16: =5000/200 -> 25 | P16: =O16*O11 -> 5037500 | Q16: 11.022338
E17: 742 | F17: =DEMANDA_PREVISIÓN!E746 -> 31 | H17: 150 | J17: 200 | L17: 20 | M17: 800 | N17: =J17/L17 -> 10 | O17: en 1 año(promedio) | Q17: 11.031944
E18: 743 | F18: =DEMANDA_PREVISIÓN!E747 -> 46 | H18: =H17-F18 -> 104 | J18: 200 | L18: 20 | M18: 800 | N18: =J18/L18 -> 10 | Q18: 11.041551
E19: 744 | F19: =DEMANDA_PREVISIÓN!E748 -> 47 | H19: =H18-F19 -> 57 | J19: 200 | L19: 20 | M19: 800 | N19: =J19/L19 -> 10 | Q19: 11.051157
E20: 745 | F20: =DEMANDA_PREVISIÓN!E749 -> 34 | H20: =H19-F20 -> 23 | I20: 200 | J20: 200 | L20: 20 | M20: 800 | N20: =J20/L20 -> 10 | Q20: 11.060764
E21: 746 | F21: =DEMANDA_PREVISIÓN!E750 -> 41 | H21: 0 | I21: 200 | J21: 200 | L21: 20 | M21: 800 | Q21: 11.07037
E22: 747 | F22: =DEMANDA_PREVISIÓN!E751 -> 40 | H22: 0 | I22: 200 | J22: 200 | L22: 20 | M22: 800 | Q22: 11.079977
E23: 748 | F23: =DEMANDA_PREVISIÓN!E752 -> 28 | H23: 0 | I23: 200 | J23: 200 | L23: 20 | M23: 800 | Q23: 11.089583
E24: 749 | F24: =DEMANDA_PREVISIÓN!E753 -> 42 | H24: 0 | I24: 200 | J24: 200 | L24: 20 | M24: 800 | Q24: 11.09919
E25: 750 | F25: =DEMANDA_PREVISIÓN!E754 -> 32 | H25: 0 | I25: 200 | J25: 200 | L25: 20 | M25: 800 | Q25: 11.108796
E26: 751 | F26: =DEMANDA_PREVISIÓN!E755 -> 48 | H26: 0 | I26: 200 | J26: 200 | L26: 20 | M26: 800 | Q26: 11.118403
E27: 752 | F27: =DEMANDA_PREVISIÓN!E756 -> 31 | H27: 200 | J27: 200 | L27: 20 | M27: 800 | Q27: 11.128009
E28: 753 | F28: =DEMANDA_PREVISIÓN!E757 -> 48 | H28: =H27-F28 -> 152 | J28: 200 | L28: 20 | M28: 800 | Q28: 11.137616
E29: 754 | F29: =DEMANDA_PREVISIÓN!E758 -> 50 | H29: =H28-F29 -> 102 | J29: 200 | L29: 20 | M29: 800 | Q29: 11.147222
E30: 755 | F30: =DEMANDA_PREVISIÓN!E759 -> 38 | H30: =H29-F30 -> 64 | I30: 200 | J30: 200 | L30: 20 | M30: 800 | Q30: 11.156829
E31: 756 | F31: =DEMANDA_PREVISIÓN!E760 -> 31 | H31: =H30-F31 -> 33 | I31: 200 | J31: 200 | L31: 20 | M31: 800 | Q31: 11.166435
E32: 757 | F32: =DEMANDA_PREVISIÓN!E761 -> 41 | H32: 0 | I32: 200 | J32: 200 | L32: 20 | M32: 800 | Q32: 11.176042
E33: 758 | F33: =DEMANDA_PREVISIÓN!E762 -> 44 | H33: 0 | I33: 200 | J33: 200 | L33: 20 | M33: 800 | Q33: 11.185648
E34: 759 | F34: =DEMANDA_PREVISIÓN!E763 -> 34 | H34: 0 | I34: 200 | J34: 200 | L34: 20 | M34: 800 | Q34: 11.195255
E35: 760 | F35: =DEMANDA_PREVISIÓN!E764 -> 34 | H35: 0 | I35: 200 | J35: 200 | L35: 20 | M35: 800 | Q35: 11.204861
E36: 761 | F36: =DEMANDA_PREVISIÓN!E765 -> 49 | H36: 0 | I36: 200 | J36: 200 | L36: 20 | M36: 800 | Q36: 11.214468
D37: Febrero | E37: 762 | F37: =DEMANDA_PREVISIÓN!E766 -> 41 | H37: 200 | J37: 200 | L37: 20 | M37: 800 | Q37: 11.224074
E38: 763 | F38: =DEMANDA_PREVISIÓN!E767 -> 40 | H38: =H37-F38 -> 160 | J38: 200 | L38: 20 | M38: 800 | Q38: 11.233681
E39: 764 | F39: =DEMANDA_PREVISIÓN!E768 -> 46 | H39: =H38-F39 -> 114 | J39: 200 | L39: 20 | M39: 800 | Q39: 11.243287
E40: 765 | F40: =DEMANDA_PREVISIÓN!E769 -> 31 | H40: =H39-F40 -> 83 | I40: 200 | J40: 200 | L40: 20 | M40: 800 | Q40: 11.252894
E41: 766 | F41: =DEMANDA_PREVISIÓN!E770 -> 38 | H41: =H40-F41 -> 45 | I41: 200 | J41: 200 | L41: 20 | M41: 800 | Q41: 11.2625
E42: 767 | F42: =DEMANDA_PREVISIÓN!E771 -> 39 | H42: =H41-F42 -> 6 | I42: 200 | J42: 200 | L42: 20 | M42: 800 | Q42: 11.272106
E43: 768 | F43: =DEMANDA_PREVISIÓN!E772 -> 40 | H43: 0 | I43: 200 | J43: 200 | L43: 20 | M43: 800 | Q43: 11.281713
E44: 769 | F44: =DEMANDA_PREVISIÓN!E773 -> 48 | H44: 0 | I44: 200 | J44: 200 | L44: 20 | M44: 800 | Q44: 11.291319
E45: 770 | F45: =DEMANDA_PREVISIÓN!E774 -> 39 | H45: 0 | I45: 200 | J45: 200 | L45: 20 | M45: 800 | Q45: 11.300926
E46: 771 | F46: =DEMANDA_PREVISIÓN!E775 -> 42 | H46: 0 | I46: 200 | J46: 200 | L46: 20 | M46: 800 | Q46: 11.310532
E47: 772 | F47: =DEMANDA_PREVISIÓN!E776 -> 43 | H47: 200 | J47: 200 | L47: 20 | M47: 800 | Q47: 11.320139
E48: 773 | F48: =DEMANDA_PREVISIÓN!E777 -> 48 | H48: =H47-F48 -> 152 | J48: 200 | L48: 20 | M48: 800 | Q48: 11.329745
E49: 774 | F49: =DEMANDA_PREVISIÓN!E778 -> 45 | H49: =H48-F49 -> 107 | J49: 200 | L49: 20 | M49: 800 | Q49: 11.339352
E50: 775 | F50: =DEMANDA_PREVISIÓN!E779 -> 53 | H50: =H49-F50 -> 54 | I50: 200 | J50: 200 | L50: 20 | M50: 800 | Q50: 11.348958
E51: 776 | F51: =DEMANDA_PREVISIÓN!E780 -> 27 | H51: =H50-F51 -> 27 | I51: 200 | J51: 200 | L51: 20 | M51: 800 | Q51: 11.358565
E52: 777 | F52: =DEMANDA_PREVISIÓN!E781 -> 38 | H52: 0 | I52: 200 | J52: 200 | L52: 20 | M52: 800 | Q52: 11.368171
E53: 778 | F53: =DEMANDA_PREVISIÓN!E782 -> 40 | H53: 0 | I53: 200 | J53: 200 | L53: 20 | M53: 800 | Q53: 11.377778
E54: 779 | F54: =DEMANDA_PREVISIÓN!E783 -> 38 | H54: 0 | I54: 200 | J54: 200 | L54: 20 | M54: 800 | Q54: 11.387384
E55: 780 | F55: =DEMANDA_PREVISIÓN!E784 -> 40 | H55: 0 | I55: 200 | J55: 200 | L55: 20 | M55: 800 | Q55: 11.396991
E56: 781 | F56: =DEMANDA_PREVISIÓN!E785 -> 36 | H56: 0 | I56: 200 | J56: 200 | L56: 20 | M56: 800 | Q56: 11.406597
E57: 782 | F57: =DEMANDA_PREVISIÓN!E786 -> 45 | H57: 200 | J57: 200 | L57: 20 | M57: 800 | Q57: 11.416204
E58: 783 | F58: =DEMANDA_PREVISIÓN!E787 -> 38 | H58: =H57-F58 -> 162 | J58: 200 | L58: 20 | M58: 800 | Q58: 11.42581
E59: 784 | F59: =DEMANDA_PREVISIÓN!E788 -> 36 | H59: =H58-F59 -> 126 | J59: 200 | L59: 20 | M59: 800 | Q59: 11.435417
E60: 785 | F60: =DEMANDA_PREVISIÓN!E789 -> 51 | H60: =H59-F60 -> 75 | I60: 200 | J60: 200 | L60: 20 | M60: 800 | Q60: 11.445023
E61: 786 | F61: =DEMANDA_PREVISIÓN!E790 -> 45 | H61: =H60-F61 -> 30 | I61: 200 | J61: 200 | L61: 20 | M61: 800 | Q61: 11.45463
E62: 787 | F62: =DEMANDA_PREVISIÓN!E791 -> 36 | H62: 0 | I62: 200 | J62: 200 | L62: 20 | M62: 800 | Q62: 11.464236
E63: 788 | F63: =DEMANDA_PREVISIÓN!E792 -> 40 | H63: 0 | I63: 200 | J63: 200 | L63: 20 | M63: 800 | Q63: 11.473843
E64: 789 | F64: =DEMANDA_PREVISIÓN!E793 -> 42 | H64: 0 | I64: 200 | J64: 200 | L64: 20 | M64: 800 | Q64: 11.483449
D65: Marzo | E65: 790 | F65: =DEMANDA_PREVISIÓN!E794 -> 39 | H65: 0 | I65: 200 | J65: 200 | L65: 20 | M65: 800 | Q65: 11.493056
E66: 791 | F66: =DEMANDA_PREVISIÓN!E795 -> 37 | H66: 0 | I66: 200 | J66: 200 | L66: 20 | M66: 800 | Q66: 11.502662
E67: 792 | F67: =DEMANDA_PREVISIÓN!E796 -> 35 | H67: 200 | J67: 200 | L67: 20 | M67: 800 | Q67: 11.512269
E68: 793 | F68: =DEMANDA_PREVISIÓN!E797 -> 39 | H68: =H67-F68 -> 161 | J68: 200 | L68: 20 | M68: 800 | Q68: 11.521875
E69: 794 | F69: =DEMANDA_PREVISIÓN!E798 -> 39 | H69: =H68-F69 -> 122 | J69: 200 | L69: 20 | M69: 800 | Q69: 11.531481
E70: 795 | F70: =DEMANDA_PREVISIÓN!E799 -> 45 | H70: =H69-F70 -> 77 | I70: 200 | J70: 200 | L70: 20 | M70: 800 | Q70: 11.541088
E71: 796 | F71: =DEMANDA_PREVISIÓN!E800 -> 34 | H71: =H70-F71 -> 43 | I71: 200 | J71: 200 | L71: 20 | M71: 800 | Q71: 11.550694
E72: 797 | F72: =DEMANDA_PREVISIÓN!E801 -> 51 | H72: 0 | I72: 200 | J72: 200 | L72: 20 | M72: 800 | Q72: 11.560301
E73: 798 | F73: =DEMANDA_PREVISIÓN!E802 -> 36 | H73: 0 | I73: 200 | J73: 200 | L73: 20 | M73: 800 | Q73: 11.569907
E74: 799 | F74: =DEMANDA_PREVISIÓN!E803 -> 37 | H74: 0 | I74: 200 | J74: 200 | L74: 20 | M74: 800 | Q74: 11.579514
E75: 800 | F75: =DEMANDA_PREVISIÓN!E804 -> 47 | H75: 0 | I75: 200 | J75: 200 | L75: 20 | M75: 800 | Q75: 11.58912
E76: 801 | F76: =DEMANDA_PREVISIÓN!E805 -> 41 | H76: 0 | I76: 200 | J76: 200 | L76: 20 | M76: 800 | Q76: 11.598727
E77: 802 | F77: =DEMANDA_PREVISIÓN!E806 -> 41 | H77: 200 | J77: 200 | L77: 20 | M77: 800 | Q77: 11.608333
E78: 803 | F78: =DEMANDA_PREVISIÓN!E807 -> 42 | H78: =H77-F78 -> 158 | J78: 200 | L78: 20 | M78: 800 | Q78: 11.61794
E79: 804 | F79: =DEMANDA_PREVISIÓN!E808 -> 48 | H79: =H78-F79 -> 110 | J79: 200 | L79: 20 | M79: 800 | Q79: 11.627546
E80: 805 | F80: =DEMANDA_PREVISIÓN!E809 -> 55 | H80: =H79-F80 -> 55 | I80: 200 | J80: 200 | L80: 20 | M80: 800 | Q80: 11.637153
E81: 806 | F81: =DEMANDA_PREVISIÓN!E810 -> 50 | H81: =H80-F81 -> 5 | I81: 200 | J81: 200 | L81: 20 | M81: 800 | Q81: 11.646759
E82: 807 | F82: =DEMANDA_PREVISIÓN!E811 -> 44 | H82: 0 | I82: 200 | J82: 200 | L82: 20 | M82: 800 | Q82: 11.656366
E83: 808 | F83: =DEMANDA_PREVISIÓN!E812 -> 41 | H83: 0 | I83: 200 | J83: 200 | L83: 20 | M83: 800 | Q83: 11.665972
E84: 809 | F84: =DEMANDA_PREVISIÓN!E813 -> 38 | H84: 0 | I84: 200 | J84: 200 | L84: 20 | M84: 800 | Q84: 11.675579
E85: 810 | F85: =DEMANDA_PREVISIÓN!E814 -> 44 | H85: 0 | I85: 200 | J85: 200 | L85: 20 | M85: 800 | Q85: 11.685185
E86: 811 | F86: =DEMANDA_PREVISIÓN!E815 -> 39 | H86: 0 | I86: 200 | J86: 200 | L86: 20 | M86: 800 | Q86: 11.694792
E87: 812 | F87: =DEMANDA_PREVISIÓN!E816 -> 52 | H87: 200 | J87: 200 | L87: 20 | M87: 800 | Q87: 11.704398
E88: 813 | F88: =DEMANDA_PREVISIÓN!E817 -> 47 | H88: =H87-F88 -> 153 | J88: 200 | L88: 20 | M88: 800 | Q88: 11.714005
E89: 814 | F89: =DEMANDA_PREVISIÓN!E818 -> 43 | H89: =H88-F89 -> 110 | J89: 200 | L89: 20 | M89: 800 | Q89: 11.723611
E90: 815 | F90: =DEMANDA_PREVISIÓN!E819 -> 56 | H90: =H89-F90 -> 54 | I90: 200 | J90: 200 | L90: 20 | M90: 800 | Q90: 11.733218
E91: 816 | F91: =DEMANDA_PREVISIÓN!E820 -> 45 | H91: =H90-F91 -> 9 | I91: 200 | J91: 200 | L91: 20 | M91: 800 | Q91: 11.742824
E92: 817 | F92: =DEMANDA_PREVISIÓN!E821 -> 49 | H92: 0 | I92: 200 | J92: 200 | L92: 20 | M92: 800 | Q92: 11.752431
E93: 818 | F93: =DEMANDA_PREVISIÓN!E822 -> 43 | H93: 0 | I93: 200 | J93: 200 | L93: 20 | M93: 800 | Q93: 11.762037
E94: 819 | F94: =DEMANDA_PREVISIÓN!E823 -> 47 | H94: 0 | I94: 200 | J94: 200 | L94: 20 | M94: 800 | Q94: 11.771644
E95: 820 | F95: =DEMANDA_PREVISIÓN!E824 -> 44 | H95: 0 | I95: 200 | J95: 200 | L95: 20 | M95: 800 | Q95: 11.78125
C96: II | D96: Abril | E96: 821 | F96: =DEMANDA_PREVISIÓN!E825 -> 42 | H96: 0 | I96: 200 | J96: 200 | L96: 20 | M96: 800 | Q96: 11.790856
E97: 822 | F97: =DEMANDA_PREVISIÓN!E826 -> 49 | H97: =I96 -> 200 | J97: 200 | L97: 20 | M97: 800 | Q97: 11.800463
E98: 823 | F98: =DEMANDA_PREVISIÓN!E827 -> 43 | H98: =H97-F98 -> 157 | J98: 200 | L98: 20 | M98: 800 | Q98: 11.810069
E99: 824 | F99: =DEMANDA_PREVISIÓN!E828 -> 29 | H99: =H98-F99 -> 128 | J99: 200 | L99: 20 | M99: 800 | Q99: 11.819676
E100: 825 | F100: =DEMANDA_PREVISIÓN!E829 -> 32 | H100: =H99-F100 -> 96 | I100: 200 | J100: 200 | L100: 20 | M100: 800 | Q100: 11.829282
E101: 826 | F101: =DEMANDA_PREVISIÓN!E830 -> 36 | H101: =H100-F101 -> 60 | I101: 200 | J101: 400 | L101: 50 | M101: 800 | Q101: 11.838889
E102: 827 | F102: =DEMANDA_PREVISIÓN!E831 -> 51 | H102: =H101-F102 -> 9 | I102: 200 | J102: 400 | L102: 50 | M102: 800 | Q102: 11.848495
E103: 828 | F103: =DEMANDA_PREVISIÓN!E832 -> 44 | H103: 0 | I103: 200 | J103: 400 | L103: 50 | M103: 800 | Q103: 11.858102
...

Sheet PROYECCIÓN_CONTINUA_BORRADOR
N1: PRODUCCIÓN CONTINUA
T2: TEMPORADA BAJA - LOTES GRANDES
N3: PRODUCCIÓN POR LOTES
B4: TRIMESTRE | C4: MES | D4: DIA | E4: DEMANDA | G4: ALMACEN | H4: CAMION | I4: EN PROCESO | K4: CAPACIDAD | L4: ROP | R4: ROP
B5: I | C5: 1 | D5: 730 | E5: =DEMANDA_PREVISIÓN!D734 -> 24 | G5: 0 | H5: 150 | I5: 150 | K5: 20 | N5: ROP | O5: 150 | Q5: CAMBIAR | R5: =H5+K5 -> 170
D6: 731 | E6: =DEMANDA_PREVISIÓN!E735 -> 44 | G6: 0 | H6: 150 | I6: 150 | K6: 20 | W6: **EDITAR
D7: 732 | E7: =DEMANDA_PREVISIÓN!E736 -> 41 | G7: 0 | H7: 150 | I7: 150 | K7: 20
D8: 733 | E8: =DEMANDA_PREVISIÓN!E737 -> 41 | G8: 0 | H8: 150 | I8: 150 | K8: 20 | N8: 150 | O8: lote
D9: 734 | E9: =DEMANDA_PREVISIÓN!E738 -> 54 | G9: 150 | I9: 150 | K9: 20 | T9: Si quiero que este en constante proceso, el ROE debe ser alto
D10: 735 | E10: =DEMANDA_PREVISIÓN!E739 -> 40 | G10: =G9-E10 -> 110 | H10: 150 | I10: 150 | K10: 20 | N10: 20 | O10: capacidad | S10: T1 | T10: Punto de reorden ALTO
C11: 2 | D11: 736 | E11: =DEMANDA_PREVISIÓN!E740 -> 46 | G11: =G10-E11 -> 64 | H11: 150 | I11: 200 | K11: 20 | S11: T2 | T11: Punto de reorden ALTO
D12: 737 | E12: =DEMANDA_PREVISIÓN!E741 -> 33 | G12: =G11-E12 -> 31 | H12: 150 | I12: 200 | K12: 20 | S12: T3 | T12: Punto de reorden ALTO
D13: 738 | E13: =DEMANDA_PREVISIÓN!E742 -> 46 | G13: 0 | H13: 150 | I13: 200 | K13: 20 | N13: =N8/N10 -> 7.5 | O13: días | S13: T4 | T13: Punto de reorden ALTO
D14: 739 | E14: =DEMANDA_PREVISIÓN!E743 -> 37 | G14: 0 | H14: 150 | I14: 200 | K14: 20 | N14: 7 | S14: T5 | T14: Punto de reorden BAJO
D15: 740 | E15: =DEMANDA_PREVISIÓN!E744 -> 35 | G15: 0 | H15: 150 | I15: 200 | K15: 20 | N15: =14.5 -> 14.5 | O15: días | S15: T6 | T15: Punto de reorden BAJO
D16: 741 | E16: =DEMANDA_PREVISIÓN!E745 -> 37 | G16: 0 | H16: 150 | I16: 200 | K16: 20 | S16: T7 | T16: Punto de reorden MEDIO
D17: 742 | E17: =DEMANDA_PREVISIÓN!E746 -> 31 | G17: 150 | I17: 200 | K17: 20 | S17: T8 | T17: Punto de reorden BAJO
D18: 743 | E18: =DEMANDA_PREVISIÓN!E747 -> 46 | G18: =G17-E18 -> 104 | I18: 200 | K18: 20
D19: 744 | E19: =DEMANDA_PREVISIÓN!E748 -> 47 | G19: =G18-E19 -> 57 | I19: 200 | K19: 20 | N19: 400 | S19: Alto producción continua
D20: 745 | E20: =DEMANDA_PREVISIÓN!E749 -> 34 | G20: =G19-E20 -> 23 | H20: 200 | I20: 200 | K20: 20 | S20: Bajo para tener días de producción
D21: 746 | E21: =DEMANDA_PREVISIÓN!E750 -> 41 | G21: 0 | H21: 200 | I21: 200 | K21: 200 | N21: 80
D22: 747 | E22: =DEMANDA_PREVISIÓN!E751 -> 40 | G22: 0 | H22: 200 | I22: 200 | K22: 200 | S22: CAMBIAR LA CANTIDAD DE PRODUCCIÓN - TEMPORADA BAJA
D23: 748 | E23: =DEMANDA_PREVISIÓN!E752 -> 28 | G23: 0 | H23: 200 | I23: 200 | K23: 200 | N23: =N19/N21 -> 5 | O23: días | U23: Tener almenos algo de inventario (Se logra teniendo un punto de reorden alto)
D24: 749 | E24: =DEMANDA_PREVISIÓN!E753 -> 42 | G24: 0 | H24: 200 | I24: 200 | K24: 200
D25: 750 | E25: =DEMANDA_PREVISIÓN!E754 -> 32 | G25: 0 | H25: 200 | I25: 200 | K25: 200 | O25: 14 minutos
D26: 751 | E26: =DEMANDA_PREVISIÓN!E755 -> 48 | G26: 0 | H26: 200 | I26: 200 | K26: 200
D27: 752 | E27: =DEMANDA_PREVISIÓN!E756 -> 31 | G27: 200 | I27: 200 | K27: 200 | N27: ROP | O27: 200
D28: 753 | E28: =DEMANDA_PREVISIÓN!E757 -> 48 | G28: =G27-E28 -> 152 | I28: 200 | K28: 200
D29: 754 | E29: =DEMANDA_PREVISIÓN!E758 -> 50 | G29: =G28-E29 -> 102 | I29: 200 | K29: 200
D30: 755 | E30: =DEMANDA_PREVISIÓN!E759 -> 38 | G30: =G29-E30 -> 64 | H30: 200 | I30: 200 | K30: 200 | O30: CAMION O CORREO
D31: 756 | E31: =DEMANDA_PREVISIÓN!E760 -> 31 | G31: =G30-E31 -> 33 | H31: 200 | I31: 200 | K31: 20
D32: 757 | E32: =DEMANDA_PREVISIÓN!E761 -> 41 | G32: 0 | H32: 200 | I32: 200 | K32: 20 | N32: FABRICA | O32: CAMIÓN | P32: INVENTARIO | R32: CLIENTE
D33: 758 | E33: =DEMANDA_PREVISIÓN!E762 -> 44 | G33: 0 | H33: 200 | I33: 200 | K33: 20 | Q33: 150
D34: 759 | E34: =DEMANDA_PREVISIÓN!E763 -> 34 | G34: 0 | H34: 200 | I34: 200 | K34: 20
D35: 760 | E35: =DEMANDA_PREVISIÓN!E764 -> 34 | G35: 0 | H35: 200 | I35: 200 | K35: 20
D36: 761 | E36: =DEMANDA_PREVISIÓN!E765 -> 49 | G36: 0 | H36: 200 | I36: 200 | K36: 20
D37: 762 | E37: =DEMANDA_PREVISIÓN!E766 -> 41 | G37: 200 | I37: 200 | K37: 20
D38: 763 | E38: =DEMANDA_PREVISIÓN!E767 -> 40 | G38: =G37-E38 -> 160 | I38: 200 | K38: 20
D39: 764 | E39: =DEMANDA_PREVISIÓN!E768 -> 46 | G39: =G38-E39 -> 114 | I39: 200 | K39: 20
D40: 765 | E40: =DEMANDA_PREVISIÓN!E769 -> 31 | G40: =G39-E40 -> 83 | H40: 200 | I40: 200 | K40: 20
C41: 3 | D41: 766 | E41: =DEMANDA_PREVISIÓN!E770 -> 38 | G41: =G40-E41 -> 45 | H41: 200 | I41: 200 | K41: 20
D42: 767 | E42: =DEMANDA_PREVISIÓN!E771 -> 39 | G42: =G41-E42 -> 6 | H42: 200 | I42: 200 | K42: 20
D43: 768 | E43: =DEMANDA_PREVISIÓN!E772 -> 40 | G43: 0 | H43: 200 | I43: 200 | K43: 20
D44: 769 | E44: =DEMANDA_PREVISIÓN!E773 -> 48 | G44: 0 | H44: 200 | I44: 200 | K44: 20
D45: 770 | E45: =DEMANDA_PREVISIÓN!E774 -> 39 | G45: 0 | H45: 200 | I45: 200 | K45: 20
D46: 771 | E46: =DEMANDA_PREVISIÓN!E775 -> 42 | G46: 0 | H46: 200 | I46: 200 | K46: 20
D47: 772 | E47: =DEMANDA_PREVISIÓN!E776 -> 43 | G47: 200 | I47: 200 | K47: 20
D48: 773 | E48: =DEMANDA_PREVISIÓN!E777 -> 48 | G48: =G47-E48 -> 152 | I48: 200 | K48: 20
D49: 774 | E49: =DEMANDA_PREVISIÓN!E778 -> 45 | G49: =G48-E49 -> 107 | I49: 200 | K49: 20
D50: 775 | E50: =DEMANDA_PREVISIÓN!E779 -> 53 | G50: =G49-E50 -> 54 | H50: 200 | I50: 200 | K50: 20
D51: 776 | E51: =DEMANDA_PREVISIÓN!E780 -> 27 | G51: =G50-E51 -> 27 | H51: 200 | I51: 200 | K51: 20
D52: 777 | E52: =DEMANDA_PREVISIÓN!E781 -> 38 | G52: 0 | H52: 200 | I52: 200 | K52: 20
D53: 778 | E53: =DEMANDA_PREVISIÓN!E782 -> 40 | G53: 0 | H53: 200 | I53: 200 | K53: 20
D54: 779 | E54: =DEMANDA_PREVISIÓN!E783 -> 38 | G54: 0 | H54: 200 | I54: 200 | K54: 20
D55: 780 | E55: =DEMANDA_PREVISIÓN!E784 -> 40 | G55: 0 | H55: 200 | I55: 200 | K55: 20
D56: 781 | E56: =DEMANDA_PREVISIÓN!E785 -> 36 | G56: 0 | H56: 200 | I56: 200 | K56: 20
D57: 782 | E57: =DEMANDA_PREVISIÓN!E786 -> 45 | G57: 200 | I57: 200 | K57: 20
D58: 783 | E58: =DEMANDA_PREVISIÓN!E787 -> 38 | G58: =G57-E58 -> 162 | I58: 200 | K58: 20
D59: 784 | E59: =DEMANDA_PREVISIÓN!E788 -> 36 | G59: =G58-E59 -> 126 | I59: 200 | K59: 20
D60: 785 | E60: =DEMANDA_PREVISIÓN!E789 -> 51 | G60: =G59-E60 -> 75 | H60: 200 | I60: 200 | K60: 20
D61: 786 | E61: =DEMANDA_PREVISIÓN!E790 -> 45 | G61: =G60-E61 -> 30 | H61: 200 | I61: 200 | K61: 20
D62: 787 | E62: =DEMANDA_PREVISIÓN!E791 -> 36 | G62: 0 | H62: 200 | I62: 200 | K62: 20
D63: 788 | E63: =DEMANDA_PREVISIÓN!E792 -> 40 | G63: 0 | H63: 200 | I63: 200 | K63: 20
D64: 789 | E64: =DEMANDA_PREVISIÓN!E793 -> 42 | G64: 0 | H64: 200 | I64: 200 | K64: 20
D65: 790 | E65: =DEMANDA_PREVISIÓN!E794 -> 39 | G65: 0 | H65: 200 | I65: 200 | K65: 20
D66: 791 | E66: =DEMANDA_PREVISIÓN!E795 -> 37 | G66: 0 | H66: 200 | I66: 200 | K66: 20
D67: 792 | E67: =DEMANDA_PREVISIÓN!E796 -> 35 | G67: 200 | I67: 200 | K67: 20
D68: 793 | E68: =DEMANDA_PREVISIÓN!E797 -> 39 | G68: =G67-E68 -> 161 | I68: 200 | K68: 20
D69: 794 | E69: =DEMANDA_PREVISIÓN!E798 -> 39 | G69: =G68-E69 -> 122 | I69: 200 | K69: 20
D70: 795 | E70: =DEMANDA_PREVISIÓN!E799 -> 45 | G70: =G69-E70 -> 77 | H70: 200 | I70: 200 | K70: 20
C71: 4 | D71: 796 | E71: =DEMANDA_PREVISIÓN!E800 -> 34 | G71: =G70-E71 -> 43 | H71: 200 | I71: 200 | K71: 20
D72: 797 | E72: =DEMANDA_PREVISIÓN!E801 -> 51 | G72: 0 | H72: 200 | I72: 200 | K72: 20
D73: 798 | E73: =DEMANDA_PREVISIÓN!E802 -> 36 | G73: 0 | H73: 200 | I73: 200 | K73: 20
D74: 799 | E74: =DEMANDA_PREVISIÓN!E803 -> 37 | G74: 0 | H74: 200 | I74: 200 | K74: 20
D75: 800 | E75: =DEMANDA_PREVISIÓN!E804 -> 47 | G75: 0 | H75: 200 | I75: 200 | K75: 20
D76: 801 | E76: =DEMANDA_PREVISIÓN!E805 -> 41 | G76: 0 | H76: 200 | I76: 200 | K76: 20
D77: 802 | E77: =DEMANDA_PREVISIÓN!E806 -> 41 | G77: 200 | I77: 200 | K77: 20
D78: 803 | E78: =DEMANDA_PREVISIÓN!E807 -> 42 | G78: =G77-E78 -> 158 | I78: 200 | K78: 20
D79: 804 | E79: =DEMANDA_PREVISIÓN!E808 -> 48 | G79: =G78-E79 -> 110 | I79: 200 | K79: 20
D80: 805 | E80: =DEMANDA_PREVISIÓN!E809 -> 55 | G80: =G79-E80 -> 55 | H80: 200 | I80: 200 | K80: 20
D81: 806 | E81: =DEMANDA_PREVISIÓN!E810 -> 50 | G81: =G80-E81 -> 5 | H81: 200 | I81: 200 | K81: 20
D82: 807 | E82: =DEMANDA_PREVISIÓN!E811 -> 44 | G82: 0 | H82: 200 | I82: 200 | K82: 20
D83: 808 | E83: =DEMANDA_PREVISIÓN!E812 -> 41 | G83: 0 | H83: 200 | I83: 200 | K83: 20
D84: 809 | E84: =DEMANDA_PREVISIÓN!E813 -> 38 | G84: 0 | H84: 200 | I84: 200 | K84: 20
D85: 810 | E85: =DEMANDA_PREVISIÓN!E814 -> 44 | G85: 0 | H85: 200 | I85: 200 | K85: 20
D86: 811 | E86: =DEMANDA_PREVISIÓN!E815 -> 39 | G86: 0 | H86: 200 | I86: 200 | K86: 20
D87: 812 | E87: =DEMANDA_PREVISIÓN!E816 -> 52 | G87: 200 | I87: 200 | K87: 20
D88: 813 | E88: =DEMANDA_PREVISIÓN!E817 -> 47 | G88: =G87-E88 -> 153 | I88: 200 | K88: 20
D89: 814 | E89: =DEMANDA_PREVISIÓN!E818 -> 43 | G89: =G88-E89 -> 110 | I89: 200 | K89: 20
D90: 815 | E90: =DEMANDA_PREVISIÓN!E819 -> 56 | G90: =G89-E90 -> 54 | H90: 200 | I90: 200 | K90: 20
D91: 816 | E91: =DEMANDA_PREVISIÓN!E820 -> 45 | G91: =G90-E91 -> 9 | H91: 200 | I91: 200 | K91: 20
D92: 817 | E92: =DEMANDA_PREVISIÓN!E821 -> 49 | G92: 0 | H92: 200 | I92: 200 | K92: 20
D93: 818 | E93: =DEMANDA_PREVISIÓN!E822 -> 43 | G93: 0 | H93: 200 | I93: 200 | K93: 20
D94: 819 | E94: =DEMANDA_PREVISIÓN!E823 -> 47 | G94: 0 | H94: 200 | I94: 200 | K94: 20
B95: II | D95: 820 | E95: =DEMANDA_PREVISIÓN!E824 -> 44 | G95: 0 | H95: 200 | I95: 200 | K95: 20 | R95: Día donde la capacidad aumente
D96: 821 | E96: =DEMANDA_PREVISIÓN!E825 -> 42 | G96: 0 | H96: 200 | I96: 200 | K96: 20 | N96: ROP | O96: 400
D97: 822 | E97: =DEMANDA_PREVISIÓN!E826 -> 49 | G97: =H96 -> 200 | I97: 200 | K97: 20
D98: 823 | E98: =DEMANDA_PREVISIÓN!E827 -> 43 | G98: =G97-E98 -> 157 | I98: 200 | K98: 20
D99: 824 | E99: =DEMANDA_PREVISIÓN!E828 -> 29 | G99: =G98-E99 -> 128 | I99: 200 | K99: 20
D100: 825 | E100: =DEMANDA_PREVISIÓN!E829 -> 32 | G100: =G99-E100 -> 96 | H100: 200 | I100: 200 | K100: 20
...

Sheet BITÁCORA
B3: N° | C3: DÍA (REAL) | D3: ENCARGADO | E3: TRIMESTRE (SIMULACIÓN) | F3: DÍA (SIMULACIÓN) | G3: PARÁMETRO | H3: NUEVO VALOR
B4: 1 | C4: 45923 | E4: T1
B5: 2
B6: 3
B7: 4 | C7: 45924 | E7: T2
B8: 5
B9: 6
B10: 7
B11: 8 | C11: 45925 | E11: T4
B12: 9
B13: 10
B14: 11 | C14: 45926 | E14: T5
B15: 12
B16: 13
B17: 14
B18: 15 | C18: 45927 | E18: T6
B19: 17
B20: 18 | C20: 45928 | E20: T7
B21: 19
B22: 20
B23: 21
B24: 22
B25: 25 | C25: 45929 | E25: T8
B26: 26
B27: 27
B28: 28
B29: 29
B30: 30
B31: 31
B32: 32 | C32: 45930
B33: 33
B34: 34
B35: 35
B36: 36
